{
  "m_GameObject": {
    "m_FileID": 0,
    "m_PathID": 1500064005264718492
  },
  "m_Enabled": 1,
  "m_Script": {
    "m_FileID": 0,
    "m_PathID": -7174338393995262336
  },
  "m_Name": "",
  "configs": [
    {
      "targetObject": {
        "m_FileID": 0,
        "m_PathID": -7750823798836129094
      },
      "ratio": 0.8
    },
    {
      "targetObject": {
        "m_FileID": 0,
        "m_PathID": 7678341090691457411
      },
      "ratio": 0.7
    },
    {
      "targetObject": {
        "m_FileID": 0,
        "m_PathID": -8976016134156651366
      },
      "ratio": 0.6
    },
    {
      "targetObject": {
        "m_FileID": 0,
        "m_PathID": -2250513644148013604
      },
      "ratio": 0.5
    },
    {
      "targetObject": {
        "m_FileID": 0,
        "m_PathID": -1764133073098692928
      },
      "ratio": 0.3
    }
  ]
}