{
  "m_GameObject": {
    "m_FileID": 0,
    "m_PathID": 8429211786378813456
  },
  "m_Enabled": 1,
  "m_Script": {
    "m_FileID": 0,
    "m_PathID": -7498146963011751304
  },
  "m_Name": "",
  "useGrayScaleAllImage": 1,
  "background": {
    "m_FileID": 0,
    "m_PathID": 0
  },
  "enableSprite": {
    "m_FileID": 0,
    "m_PathID": 0
  },
  "disableSprite": {
    "m_FileID": 0,
    "m_PathID": 0
  },
  "tmpText": {
    "m_FileID": 0,
    "m_PathID": -6564522183661712921
  },
  "overrideText": 0,
  "enableTextKey": "",
  "disableTextKey": "",
  "overrideTextColor": 1,
  "enableTextColor": {
    "r": 1.0,
    "g": 1.0,
    "b": 1.0,
    "a": 1.0
  },
  "disableTextColor": {
    "r": 0.5,
    "g": 0.5,
    "b": 0.5,
    "a": 1.0
  },
  "buttonSfx": {
    "m_FileID": 0,
    "m_PathID": 446096115689295442
  },
  "enableSfxType": 0,
  "disableSfxType": 1
}