{
  "m_GameObject": {
    "m_FileID": 0,
    "m_PathID": -2366760702025999376
  },
  "m_Enabled": 1,
  "m_Script": {
    "m_FileID": 0,
    "m_PathID": -8940529911906571770
  },
  "m_Name": "",
  "ignoreList": [
    {
      "m_FileID": 0,
      "m_PathID": 1199266184586210658
    }
  ],
  "bindables": [
    {
      "m_FileID": 0,
      "m_PathID": 7517222153730887005
    },
    {
      "m_FileID": 0,
      "m_PathID": 3575046594615697388
    },
    {
      "m_FileID": 0,
      "m_PathID": 7806415503518677360
    },
    {
      "m_FileID": 0,
      "m_PathID": 3997389507341638180
    },
    {
      "m_FileID": 0,
      "m_PathID": -5677116067581157563
    },
    {
      "m_FileID": 0,
      "m_PathID": -2871070486852134685
    },
    {
      "m_FileID": 0,
      "m_PathID": 1617818434131843886
    },
    {
      "m_FileID": 0,
      "m_PathID": 7802769888963720691
    },
    {
      "m_FileID": 0,
      "m_PathID": 3506109897025802080
    },
    {
      "m_FileID": 0,
      "m_PathID": 4031557279564664668
    },
    {
      "m_FileID": 0,
      "m_PathID": 3946579723312414298
    },
    {
      "m_FileID": 0,
      "m_PathID": -7073687897729474148
    },
    {
      "m_FileID": 0,
      "m_PathID": 467731899408691384
    },
    {
      "m_FileID": 0,
      "m_PathID": 5348705517107490834
    },
    {
      "m_FileID": 0,
      "m_PathID": -6980048265712707902
    },
    {
      "m_FileID": 0,
      "m_PathID": 647148203232697682
    },
    {
      "m_FileID": 0,
      "m_PathID": 7692802725036061267
    },
    {
      "m_FileID": 0,
      "m_PathID": -5352504266267789502
    },
    {
      "m_FileID": 0,
      "m_PathID": 3234897997385316089
    },
    {
      "m_FileID": 0,
      "m_PathID": 4362949018504893963
    },
    {
      "m_FileID": 0,
      "m_PathID": 5279152872411752826
    },
    {
      "m_FileID": 0,
      "m_PathID": 5696972742983770124
    },
    {
      "m_FileID": 0,
      "m_PathID": -7022257361860168334
    },
    {
      "m_FileID": 0,
      "m_PathID": 2158228003371768991
    },
    {
      "m_FileID": 0,
      "m_PathID": 480077862790376079
    },
    {
      "m_FileID": 0,
      "m_PathID": -9067153751472676064
    },
    {
      "m_FileID": 0,
      "m_PathID": 2536621784406026203
    },
    {
      "m_FileID": 0,
      "m_PathID": 4942752796042539303
    },
    {
      "m_FileID": 0,
      "m_PathID": -2493168499306628206
    },
    {
      "m_FileID": 0,
      "m_PathID": 7085632604501947631
    },
    {
      "m_FileID": 0,
      "m_PathID": -9004424788544933353
    },
    {
      "m_FileID": 0,
      "m_PathID": 1406298782820911569
    },
    {
      "m_FileID": 0,
      "m_PathID": -8826817096182351267
    },
    {
      "m_FileID": 0,
      "m_PathID": 8852494691633786088
    },
    {
      "m_FileID": 0,
      "m_PathID": -2788393356963235991
    },
    {
      "m_FileID": 0,
      "m_PathID": 5787222263649232814
    },
    {
      "m_FileID": 0,
      "m_PathID": 5588167619272761903
    },
    {
      "m_FileID": 0,
      "m_PathID": 3710247244008324031
    }
  ]
}