{
  "m_GameObject": {
    "m_FileID": 0,
    "m_PathID": 0
  },
  "m_Enabled": 1,
  "m_Script": {
    "m_FileID": 0,
    "m_PathID": -7366290571601817769
  },
  "m_Name": "GranfaDungeonData",
  "currencyType": 6,
  "maxTicket": 20,
  "refillTicket": 2,
  "useAdRefill": 1,
  "maxAdCount": 2,
  "adType": 11,
  "dungeonInfoUIPrefab": {
    "m_FileID": 0,
    "m_PathID": -1653311438316965529
  },
  "dungeonEntranceAnimatorPrefab": {
    "m_FileID": 0,
    "m_PathID": -4554777680097430258
  },
  "backgroundSprite": {
    "m_FileID": 0,
    "m_PathID": 6089275587074904264
  },
  "ticketIconSprite": {
    "m_FileID": 0,
    "m_PathID": -3246077415259072282
  },
  "popupBannerSprite": {
    "m_FileID": 0,
    "m_PathID": -8050406814476125204
  },
  "nameKey": "DUNGEON_NAME_DWARFGRANDFATHER",
  "descKey": "DUNGEON_DESC_DWARFGRANDFATHER"
}