{
  "m_GameObject": {
    "m_FileID": 0,
    "m_PathID": -4910429106175627015
  },
  "m_Enabled": 1,
  "m_Script": {
    "m_FileID": 0,
    "m_PathID": 6236441469479178695
  },
  "m_Name": "",
  "m_Padding": {
    "m_Left": 0,
    "m_Right": 0,
    "m_Top": 9,
    "m_Bottom": 18
  },
  "m_ChildAlignment": 4,
  "m_StartCorner": 0,
  "m_StartAxis": 0,
  "m_CellSize": {
    "x": 224.41,
    "y": 180.1
  },
  "m_Spacing": {
    "x": 6.9,
    "y": 8.3
  },
  "m_Constraint": 1,
  "m_ConstraintCount": 3
}