{
  "m_GameObject": {
    "m_FileID": 0,
    "m_PathID": -4631415310524404346
  },
  "m_Enabled": 1,
  "m_Script": {
    "m_FileID": 0,
    "m_PathID": -6003642177999167765
  },
  "m_Name": "",
  "onClick": {
    "m_PersistentCalls": {
      "m_Calls": [
        {
          "m_Target": {
            "m_FileID": 0,
            "m_PathID": -1262038871190435891
          },
          "m_TargetAssemblyTypeName": "LoadComplete.UI.PanelSlimeLevelUp, Assembly-CSharp",
          "m_MethodName": "OnClick_HealthRegenLevelUp",
          "m_Mode": 1,
          "m_Arguments": {
            "m_ObjectArgument": {
              "m_FileID": 0,
              "m_PathID": 0
            },
            "m_ObjectArgumentAssemblyTypeName": "UnityEngine.Object, UnityEngine",
            "m_IntArgument": 0,
            "m_FloatArgument": 0.0,
            "m_StringArgument": "",
            "m_BoolArgument": 0
          },
          "m_CallState": 2
        }
      ]
    }
  },
  "onPressHold": {
    "m_PersistentCalls": {
      "m_Calls": [
        {
          "m_Target": {
            "m_FileID": 0,
            "m_PathID": -1262038871190435891
          },
          "m_TargetAssemblyTypeName": "LoadComplete.UI.PanelSlimeLevelUp, Assembly-CSharp",
          "m_MethodName": "OnClick_HealthRegenLevelUp",
          "m_Mode": 1,
          "m_Arguments": {
            "m_ObjectArgument": {
              "m_FileID": 0,
              "m_PathID": 0
            },
            "m_ObjectArgumentAssemblyTypeName": "UnityEngine.Object, UnityEngine",
            "m_IntArgument": 0,
            "m_FloatArgument": 0.0,
            "m_StringArgument": "",
            "m_BoolArgument": 0
          },
          "m_CallState": 2
        }
      ]
    }
  },
  "onPressExit": {
    "m_PersistentCalls": {
      "m_Calls": [
        {
          "m_Target": {
            "m_FileID": 0,
            "m_PathID": -1262038871190435891
          },
          "m_TargetAssemblyTypeName": "LoadComplete.UI.PanelSlimeLevelUp, Assembly-CSharp",
          "m_MethodName": "OnPointerUp_LevelUp",
          "m_Mode": 1,
          "m_Arguments": {
            "m_ObjectArgument": {
              "m_FileID": 0,
              "m_PathID": 0
            },
            "m_ObjectArgumentAssemblyTypeName": "UnityEngine.Object, UnityEngine",
            "m_IntArgument": 0,
            "m_FloatArgument": 0.0,
            "m_StringArgument": "",
            "m_BoolArgument": 0
          },
          "m_CallState": 2
        }
      ]
    }
  },
  "repeatInterval": 0.05
}